nitrogen/__init__.py
nitrogen/angmom.py
nitrogen/cythontest.cp37-win_amd64.pyd
nitrogen/dfun.py
nitrogen/ham.py
nitrogen/math.py
nitrogen/scf.py
nitrogen/special.py
nitrogen/symmetry.py
nitrogen/tensor.py
nitrogen/autodiff/__init__.py
nitrogen/autodiff/forward.py
nitrogen/autodiff/cyad/__init__.py
nitrogen/autodiff/cyad/cyad_core.cp37-win_amd64.pyd
nitrogen/autodiff/forward/__init__.py
nitrogen/autodiff/forward/linalg.py
nitrogen/basis/__init__.py
nitrogen/basis/besDVR.py
nitrogen/basis/dvr.py
nitrogen/basis/fourDVR.py
nitrogen/basis/genericbasis.py
nitrogen/basis/hoDVR.py
nitrogen/basis/legDVR.py
nitrogen/basis/ndbasis.py
nitrogen/basis/ndbasis_c.cp37-win_amd64.pyd
nitrogen/basis/ops.py
nitrogen/basis/sincDVR.py
nitrogen/constants/__init__.py
nitrogen/constants/ame2016.py
nitrogen/constants/codata2018.py
nitrogen/coordsys/__init__.py
nitrogen/coordsys/coordsys.py
nitrogen/coordsys/frames.py
nitrogen/coordsys/jacobi.py
nitrogen/coordsys/simple_builtins.py
nitrogen/coordsys/zmat.py
nitrogen/ham/__init__.py
nitrogen/ham/dpcart.py
nitrogen/ham/generic.py
nitrogen/ham/model.py
nitrogen/linalg/__init__.py
nitrogen/linalg/linalg.py
nitrogen/linalg/packed.py
nitrogen/pes/__init__.py
nitrogen/pes/cfour.py
nitrogen/pes/lapath.py
nitrogen/pes/opt.py
nitrogen/pes/rxnpath.py
nitrogen/pes/fit/__init__.py
nitrogen/pes/fit/exppip.cp37-win_amd64.pyd
nitrogen/pes/library/H3+_MBB1986.py
nitrogen/pes/library/__init__.py
nitrogen/pes/library/co2_zbar1999.py
nitrogen/pes/library/h2o2_mk2012_ad.py
nitrogen/pes/library/h2o2_mk2012_bo.py
nitrogen/pes/library/h2o_dummy.py
nitrogen/pes/library/h2o_pjt1996.py
nitrogen/pes/library/h3cation_mbb1986.py
nitrogen/pes/library/muellerbrown.py
nitrogen/pes/library/si2c.py
nitrogen/pes/library/c2h_chptp2000/__init__.py
nitrogen/pes/library/mal_mht2014/__init__.py
nitrogen/pes/library/mal_mht2014/malpes.cp37-win_amd64.pyd
nitrogen/scf/__init__.py
nitrogen/scf/rovib.py
nitrogen/vpt/__init__.py
nitrogen/vpt/cfourvib.py
nitrogen/vpt/distho.py
nitrogen-2.2.3.dist-info/LICENSE
nitrogen-2.2.3.dist-info/METADATA
nitrogen-2.2.3.dist-info/WHEEL
nitrogen-2.2.3.dist-info/top_level.txt
nitrogen-2.2.3.dist-info/RECORD
