Metadata-Version: 2.1
Name: nitrogen
Version: 2.2.3
Summary: A scientific computing package for nuclear motion calculations of small molecules.
Home-page: https://github.com/bchangala/nitrogen
Author: Bryan Changala
Author-email: bryan.changala@cfa.harvard.edu
License: UNKNOWN
Platform: UNKNOWN
Classifier: Programming Language :: Python :: 3
Classifier: License :: OSI Approved :: MIT License
Classifier: Operating System :: OS Independent
Requires-Python: >=3.7.11
License-File: LICENSE
Requires-Dist: numpy (>=1.20.0)
Requires-Dist: scipy (>=1.4.1)
Requires-Dist: matplotlib (<3.3,>=3.1)
Requires-Dist: scikit-image
Requires-Dist: setuptools (>=49)
Requires-Dist: wheel
Requires-Dist: Cython (>=0.29.21)
Requires-Dist: py3nj (==0.1.2)
